odoo/addons/edi_product_oca/README.rst
odoo/addons/edi_product_oca/__init__.py
odoo/addons/edi_product_oca/__manifest__.py
odoo/addons/edi_product_oca/i18n/de.po
odoo/addons/edi_product_oca/i18n/edi_product_oca.pot
odoo/addons/edi_product_oca/i18n/it.po
odoo/addons/edi_product_oca/models/__init__.py
odoo/addons/edi_product_oca/models/product_packaging.py
odoo/addons/edi_product_oca/models/product_product.py
odoo/addons/edi_product_oca/models/product_template.py
odoo/addons/edi_product_oca/readme/CONTRIBUTORS.rst
odoo/addons/edi_product_oca/readme/DESCRIPTION.rst
odoo/addons/edi_product_oca/static/description/icon.png
odoo/addons/edi_product_oca/static/description/index.html
odoo/addons/edi_product_oca/views/product_packaging_views.xml
odoo/addons/edi_product_oca/views/product_views.xml
odoo_addon_edi_product_oca-16.0.1.1.1.10.dist-info/METADATA
odoo_addon_edi_product_oca-16.0.1.1.1.10.dist-info/WHEEL
odoo_addon_edi_product_oca-16.0.1.1.1.10.dist-info/top_level.txt
odoo_addon_edi_product_oca-16.0.1.1.1.10.dist-info/RECORD
