Metadata-Version: 2.1
Name: odoo-addon-edi_product_oca
Version: 16.0.1.1.1.10
Summary: EDI framework configuration and base logic for products and products packaging
Home-page: https://github.com/OCA/edi-framework
Author: ForgeFlow, Odoo Community Association (OCA)
Author-email: support@odoo-community.org
License: AGPL-3
Classifier: Programming Language :: Python
Classifier: Framework :: Odoo
Classifier: Framework :: Odoo :: 16.0
Classifier: License :: OSI Approved :: GNU Affero General Public License v3
Requires-Python: >=3.10
Requires-Dist: odoo-addon-edi-oca<16.1dev,>=16.0dev
Requires-Dist: odoo<16.1dev,>=16.0a
